trepr/__init__.py
trepr/analysis.py
trepr/dataset.py
trepr/exceptions.py
trepr/io.py
trepr/metadata_mapper.yaml
trepr/plotting.py
trepr/processing.py
trepr/report.py
trepr/tez_mapper.yaml
trepr/utils.py
trepr-0.2.0.dist-info/LICENSE
trepr-0.2.0.dist-info/METADATA
trepr-0.2.0.dist-info/WHEEL
trepr-0.2.0.dist-info/top_level.txt
trepr-0.2.0.dist-info/RECORD
