Metadata-Version: 2.1
Name: trepr
Version: 0.2.0
Summary: Package for handling tr-EPR data.
Home-page: https://www.trepr.de/
Author: Jara Popp, Mirjam Schröder, Till Biskup
Author-email: till@till-biskup.de
License: UNKNOWN
Project-URL: Documentation, https://docs.trepr.de/
Project-URL: Source, https://github.com/tillbiskup/trepr
Keywords: spectroscopy,EPR spectroscopy,time-resolved electron paramagnetic resonance,data processing and analysis,reproducible science,reproducible research,good scientific practice,recipe-driven data analysis
Platform: UNKNOWN
Classifier: Programming Language :: Python :: 3
Classifier: Programming Language :: Python :: 3.7
Classifier: Programming Language :: Python :: 3.8
Classifier: Programming Language :: Python :: 3.9
Classifier: License :: OSI Approved :: BSD License
Classifier: Operating System :: OS Independent
Classifier: Intended Audience :: Science/Research
Classifier: Development Status :: 4 - Beta
Classifier: Topic :: Scientific/Engineering
Classifier: Topic :: Software Development :: Libraries :: Application Frameworks
Requires-Python: >=3.7
Requires-Dist: aspecd (>=0.7.0)
Requires-Dist: colour
Requires-Dist: jinja2
Requires-Dist: matplotlib
Requires-Dist: numpy
Requires-Dist: scipy
Requires-Dist: xmltodict
Provides-Extra: dev
Requires-Dist: prospector ; extra == 'dev'
Provides-Extra: docs
Requires-Dist: sphinx ; extra == 'docs'
Requires-Dist: sphinx-rtd-theme ; extra == 'docs'
